sitcom_simulator/__init__.py
sitcom_simulator/auto.py
sitcom_simulator/cli.py
sitcom_simulator/models.py
sitcom_simulator/user_input.py
sitcom_simulator/image/__init__.py
sitcom_simulator/image/image_generator.py
sitcom_simulator/image/integrations/__init__.py
sitcom_simulator/image/integrations/pillow.py
sitcom_simulator/image/integrations/stability.py
sitcom_simulator/music/__init__.py
sitcom_simulator/music/music_generator.py
sitcom_simulator/music/integrations/__init__.py
sitcom_simulator/music/integrations/freepd.py
sitcom_simulator/script/__init__.py
sitcom_simulator/script/llm.py
sitcom_simulator/script/llm_instructions.txt
sitcom_simulator/script/script_generator.py
sitcom_simulator/script/integrations/__init__.py
sitcom_simulator/script/integrations/chatgpt/__init__.py
sitcom_simulator/script/integrations/chatgpt/chatgpt.py
sitcom_simulator/script/integrations/fakeyou/__init__.py
sitcom_simulator/script/integrations/fakeyou/character_extraction_instructions.txt
sitcom_simulator/script/integrations/fakeyou/character_extractor.py
sitcom_simulator/script/integrations/fakeyou/character_selector.py
sitcom_simulator/script/integrations/fakeyou/characters.toml
sitcom_simulator/script/integrations/fakeyou/curated_voices.csv
sitcom_simulator/script/integrations/fakeyou/narrators.py
sitcom_simulator/social/yt_uploader.py
sitcom_simulator/speech/__init__.py
sitcom_simulator/speech/speech_generator.py
sitcom_simulator/speech/integrations/__init__.py
sitcom_simulator/speech/integrations/fakeyou.py
sitcom_simulator/speech/integrations/gtts.py
sitcom_simulator/video/__init__.py
sitcom_simulator/video/video_generator.py
sitcom_simulator/video/integrations/__init__.py
sitcom_simulator/video/integrations/ffmpeg.py
sitcom_simulator/video/integrations/moviepy.py
sitcom_simulator-0.6.1.dist-info/METADATA
sitcom_simulator-0.6.1.dist-info/WHEEL
sitcom_simulator-0.6.1.dist-info/entry_points.txt
sitcom_simulator-0.6.1.dist-info/licenses/LICENSE
sitcom_simulator-0.6.1.dist-info/RECORD
