Metadata-Version: 2.3
Name: sitcom-simulator
Version: 0.6.1
Summary: A highly-customizable tool for automatically creating AI-generated meme videos
Project-URL: homepage, https://github.com/joshmoody24/sitcom-simulator
Project-URL: documentation, https://joshmoody24.github.io/sitcom-simulator/
Project-URL: repository, https://github.com/joshmoody24/sitcom-simulator
Author-email: Josh Moody <josh@joshmoody.org>
License: MIT License
License-File: LICENSE
Keywords: ai,generator,meme,simulator,sitcom,video
Classifier: License :: OSI Approved :: MIT License
Classifier: Operating System :: OS Independent
Classifier: Programming Language :: Python :: 3
Requires-Python: >=3.11
Requires-Dist: beautifulsoup4~=4.12.2
Requires-Dist: ffmpeg-python~=0.2.0
Requires-Dist: gtts~=2.5.1
Requires-Dist: openai~=0.28.0
Requires-Dist: pillow~=10.0.1
Requires-Dist: python-dotenv~=1.0.0
Requires-Dist: requests~=2.31.0
Requires-Dist: stability-sdk~=0.8.5
Requires-Dist: thefuzz~=0.22.1
Requires-Dist: toml
Requires-Dist: tqdm~=4.66.1
Provides-Extra: dev
Requires-Dist: furo; extra == 'dev'
Requires-Dist: mypy; extra == 'dev'
Requires-Dist: sphinx; extra == 'dev'
Requires-Dist: sphinx-autodoc-typehints; extra == 'dev'
